aliyunsdkess/__init__.py
aliyunsdkess/endpoint.py
aliyunsdkess/request/__init__.py
aliyunsdkess/request/v20140828/AttachAlbServerGroupsRequest.py
aliyunsdkess/request/v20140828/AttachDBInstancesRequest.py
aliyunsdkess/request/v20140828/AttachInstancesRequest.py
aliyunsdkess/request/v20140828/AttachLoadBalancersRequest.py
aliyunsdkess/request/v20140828/AttachServerGroupsRequest.py
aliyunsdkess/request/v20140828/AttachVServerGroupsRequest.py
aliyunsdkess/request/v20140828/ChangeResourceGroupRequest.py
aliyunsdkess/request/v20140828/CompleteLifecycleActionRequest.py
aliyunsdkess/request/v20140828/CreateAlarmRequest.py
aliyunsdkess/request/v20140828/CreateEciScalingConfigurationRequest.py
aliyunsdkess/request/v20140828/CreateLifecycleHookRequest.py
aliyunsdkess/request/v20140828/CreateNotificationConfigurationRequest.py
aliyunsdkess/request/v20140828/CreateScalingConfigurationRequest.py
aliyunsdkess/request/v20140828/CreateScalingGroupRequest.py
aliyunsdkess/request/v20140828/CreateScalingRuleRequest.py
aliyunsdkess/request/v20140828/CreateScheduledTaskRequest.py
aliyunsdkess/request/v20140828/DeactivateScalingConfigurationRequest.py
aliyunsdkess/request/v20140828/DeleteAlarmRequest.py
aliyunsdkess/request/v20140828/DeleteEciScalingConfigurationRequest.py
aliyunsdkess/request/v20140828/DeleteLifecycleHookRequest.py
aliyunsdkess/request/v20140828/DeleteNotificationConfigurationRequest.py
aliyunsdkess/request/v20140828/DeleteScalingConfigurationRequest.py
aliyunsdkess/request/v20140828/DeleteScalingGroupRequest.py
aliyunsdkess/request/v20140828/DeleteScalingRuleRequest.py
aliyunsdkess/request/v20140828/DeleteScheduledTaskRequest.py
aliyunsdkess/request/v20140828/DescribeAlarmsRequest.py
aliyunsdkess/request/v20140828/DescribeEciScalingConfigurationsRequest.py
aliyunsdkess/request/v20140828/DescribeElasticStrengthRequest.py
aliyunsdkess/request/v20140828/DescribeLifecycleActionsRequest.py
aliyunsdkess/request/v20140828/DescribeLifecycleHooksRequest.py
aliyun_python_sdk_ess-2.3.32.dist-info/LICENSE
aliyun_python_sdk_ess-2.3.32.dist-info/METADATA
aliyun_python_sdk_ess-2.3.32.dist-info/WHEEL
aliyun_python_sdk_ess-2.3.32.dist-info/top_level.txt
aliyun_python_sdk_ess-2.3.32.dist-info/RECORD
